docs/source/conf.py
spirepy/__init__.py
spirepy/data.py
spirepy/genome.py
spirepy/logger.py
spirepy/sample.py
spirepy/study.py
spirepy/util.py
spirepy/cli/__init__.py
spirepy/cli/download.py
spirepy/cli/spire.py
spirepy/cli/view.py
spirepy-0.1.0.dist-info/licenses/LICENSE
tests/integration/__init__.py
tests/integration/fixtures.py
tests/integration/test_download.py
tests/integration/test_view.py
tests/unit/__init__.py
tests/unit/fixtures.py
tests/unit/test_sample.py
tests/unit/test_study.py
spirepy-0.1.0.dist-info/METADATA
spirepy-0.1.0.dist-info/WHEEL
spirepy-0.1.0.dist-info/entry_points.txt
spirepy-0.1.0.dist-info/top_level.txt
spirepy-0.1.0.dist-info/RECORD
